cyf09_mcp_server/__init__.py
cyf09_mcp_server-0.1.0.dist-info/METADATA
cyf09_mcp_server-0.1.0.dist-info/WHEEL
cyf09_mcp_server-0.1.0.dist-info/entry_points.txt
cyf09_mcp_server-0.1.0.dist-info/RECORD
