Metadata-Version: 2.4
Name: cyf09-mcp-server
Version: 0.1.0
Summary: Add your description here
Author-email: CYF <zjw@zjw.com>
Requires-Python: >=3.13
Requires-Dist: mcp[cli]>=1.11.0
